cache_requests/__init__.py
cache_requests/_compat.py
cache_requests/memoize.py
cache_requests/sessions.py
cache_requests/utils.py
cache_requests-4.0.0.dist-info/DESCRIPTION.rst
cache_requests-4.0.0.dist-info/METADATA
cache_requests-4.0.0.dist-info/RECORD
cache_requests-4.0.0.dist-info/WHEEL
cache_requests-4.0.0.dist-info/metadata.json
cache_requests-4.0.0.dist-info/top_level.txt
