Metadata-Version: 2.0
Name: cache-requests
Version: 4.0.0
Summary: Simple. Powerful. Persistent LRU caching for the requests library.
Home-page: https://github.com/bionikspoon/cache_requests
Author: Manu Phatak
Author-email: bionikspoon@gmail.com
License: MIT
Keywords: cache_requests Manu Phatak
Platform: UNKNOWN
Classifier: Development Status :: 5 - Production/Stable
Classifier: Intended Audience :: Developers
Classifier: License :: OSI Approved :: MIT License
Classifier: Natural Language :: English
Classifier: Programming Language :: Python
Classifier: Programming Language :: Python :: 2
Classifier: Programming Language :: Python :: 2.6
Classifier: Programming Language :: Python :: 2.7
Classifier: Programming Language :: Python :: 3
Classifier: Programming Language :: Python :: 3.3
Classifier: Programming Language :: Python :: 3.4
Classifier: Programming Language :: Python :: 3.5
Classifier: Programming Language :: Python :: Implementation :: CPython
Classifier: Programming Language :: Python :: Implementation :: PyPy
Classifier: Topic :: Database
Classifier: Topic :: Database :: Database Engines/Servers
Classifier: Topic :: Internet :: WWW/HTTP
Classifier: Topic :: Internet :: WWW/HTTP :: Session
Classifier: Topic :: Internet :: WWW/HTTP :: Site Management
Classifier: Topic :: Software Development
Classifier: Topic :: Utilities
Requires-Dist: redislite
Requires-Dist: requests
Requires-Dist: six
